LICENSE
MANIFEST.in
README.md
setup.py
libpythonpro/__init__.py
libpythonpro/github_api.py
libpythonprojms.egg-info/PKG-INFO
libpythonprojms.egg-info/SOURCES.txt
libpythonprojms.egg-info/dependency_links.txt
libpythonprojms.egg-info/not-zip-safe
libpythonprojms.egg-info/requires.txt
libpythonprojms.egg-info/top_level.txt